LICENSE
README.md
setup.py
OCBO/__init__.py
OCBO/cts_ocbo.py
OCBO/ocbo.py
OCBO.egg-info/PKG-INFO
OCBO.egg-info/SOURCES.txt
OCBO.egg-info/dependency_links.txt
OCBO.egg-info/requires.txt
OCBO.egg-info/top_level.txt
OCBO/cstrats/__init__.py
OCBO/cstrats/agn_cts.py
OCBO/cstrats/cts_opt.py
OCBO/cstrats/postmax_cts.py
OCBO/cstrats/profile_cts.py
OCBO/cstrats/rand_cts.py
OCBO/cstrats/replay.py
OCBO/gp/__init__.py
OCBO/gp/gp_interface.py
OCBO/gp/gp_util.py
OCBO/gp/gpytorch_interface.py
OCBO/scripts/__init__.py
OCBO/scripts/cts_plotter.py
OCBO/scripts/discrete_plotter.py
OCBO/strategies/__init__.py
OCBO/strategies/agnostic_opt.py
OCBO/strategies/corr_opt.py
OCBO/strategies/joint_agnostic_opt.py
OCBO/strategies/joint_mei.py
OCBO/strategies/joint_mts.py
OCBO/strategies/joint_opt.py
OCBO/strategies/mei.py
OCBO/strategies/mts.py
OCBO/strategies/multi_opt.py
OCBO/strategies/random_strat.py
OCBO/synth/__init__.py
OCBO/synth/continuous_2d.py
OCBO/synth/function_generator.py
OCBO/synth/oned.py
OCBO/synth/sixd.py
OCBO/synth/twod.py
OCBO/util/__init__.py
OCBO/util/misc_util.py
OCBO/util/plotting_util.py
OCBO/util/post_util.py