Metadata-Version: 2.1
Name: OCBO
Version: 0.1.2
Summary: Offline Contextual Bayesian Optimization
Home-page: https://github.com/zhaofeng-shu33/OCBO
Author: zhaofeng-shu33
Author-email: 616545598@qq.com
License: MIT License
Platform: UNKNOWN
